audio_segmenter/__init__.py
audio_segmenter/cli.py
audio_segmenter/segmenter.py
audio_segmenter-0.1.5.dist-info/METADATA
audio_segmenter-0.1.5.dist-info/WHEEL
audio_segmenter-0.1.5.dist-info/entry_points.txt
audio_segmenter-0.1.5.dist-info/top_level.txt
audio_segmenter-0.1.5.dist-info/RECORD
